minegpt2/__init__.py
minegpt2/kogpt2/__init__.py
minegpt2/kogpt2/mxnet_kogpt2.py
minegpt2/kogpt2/pytorch_kogpt2.py
minegpt2/kogpt2/utils.py
minegpt2/kogpt2/model/__init__.py
minegpt2/kogpt2/model/gpt.py
minegpt2-0.0.2.dist-info/DESCRIPTION.rst
minegpt2-0.0.2.dist-info/METADATA
minegpt2-0.0.2.dist-info/RECORD
minegpt2-0.0.2.dist-info/WHEEL
minegpt2-0.0.2.dist-info/metadata.json
minegpt2-0.0.2.dist-info/top_level.txt
